postivo_client/__init__.py
postivo_client/_version.py
postivo_client/accounts.py
postivo_client/addressbook.py
postivo_client/basesdk.py
postivo_client/byextid.py
postivo_client/common.py
postivo_client/contacts.py
postivo_client/groups.py
postivo_client/httpclient.py
postivo_client/metadata.py
postivo_client/py.typed
postivo_client/sdk.py
postivo_client/sdkconfiguration.py
postivo_client/senders.py
postivo_client/shipments.py
postivo_client/_hooks/__init__.py
postivo_client/_hooks/registration.py
postivo_client/_hooks/sdkhooks.py
postivo_client/_hooks/types.py
postivo_client/errors/__init__.py
postivo_client/errors/clienterror.py
postivo_client/errors/errorresponse.py
postivo_client/errors/no_response_error.py
postivo_client/errors/responsevalidationerror.py
postivo_client/errors/sdkdefaulterror.py
postivo_client/models/__init__.py
postivo_client/models/accountresponse.py
postivo_client/models/addcontactbyextidtogroupop.py
postivo_client/models/addcontactop.py
postivo_client/models/addcontacttogroupop.py
postivo_client/models/addgroupop.py
postivo_client/models/addsenderop.py
postivo_client/models/cancelshipmentop.py
postivo_client/models/contact.py
postivo_client/models/contactresponse.py
postivo_client/models/deletecontactbyexternalidop.py
postivo_client/models/deletecontactop.py
postivo_client/models/deletegroupop.py
postivo_client/models/deletesenderop.py
postivo_client/models/documentlibrary.py
postivo_client/models/documentmock.py
postivo_client/models/documentpdf.py
postivo_client/models/documentresponse.py
postivo_client/models/documents.py
postivo_client/models/errorresponse.py
postivo_client/models/getaccountdetailsop.py
postivo_client/models/getcontactbyexternalidop.py
postivo_client/models/getcontactbyidop.py
postivo_client/models/getdocumentsop.py
postivo_client/models/getgroupbyidop.py
postivo_client/models/getstatusop.py
postivo_client/models/getsubaccountdetailsop.py
postivo_client/models/group.py
postivo_client/models/groupresponse.py
postivo_client-0.1.0.dist-info/licenses/LICENSE
postivo_client-0.1.0.dist-info/METADATA
postivo_client-0.1.0.dist-info/WHEEL
postivo_client-0.1.0.dist-info/top_level.txt
postivo_client-0.1.0.dist-info/RECORD
