Metadata-Version: 2.4
Name: postivo-client
Version: 0.1.0
Summary: POSTIVO.PL Hybrid Mail Services REST API Client SDK
Author: POSTIVO.PL
Requires-Python: >=3.9.2
License-File: LICENSE
Requires-Dist: httpcore>=1.0.9
Requires-Dist: httpx>=0.28.1
Requires-Dist: pydantic>=2.11.2
Dynamic: license-file
